comfy_test/__init__.py
comfy_test/__main__.py
comfy_test/runner.py
comfy_test/cli/__init__.py
comfy_test/cli/download.py
comfy_test/cli/generate.py
comfy_test/cli/info.py
comfy_test/cli/init.py
comfy_test/cli/merge.py
comfy_test/cli/pool.py
comfy_test/cli/publish.py
comfy_test/cli/run.py
comfy_test/cli/screenshot.py
comfy_test/cli/verify.py
comfy_test/comfyui/__init__.py
comfy_test/comfyui/api.py
comfy_test/comfyui/models.py
comfy_test/comfyui/server.py
comfy_test/comfyui/validator.py
comfy_test/comfyui/workflow.py
comfy_test/comfyui/workflow_converter.py
comfy_test/common/__init__.py
comfy_test/common/base_platform.py
comfy_test/common/comfy_env.py
comfy_test/common/config.py
comfy_test/common/config_file.py
comfy_test/common/errors.py
comfy_test/common/resource_monitor.py
comfy_test/github/__init__.py
comfy_test/github/local_runner.py
comfy_test/orchestration/__init__.py
comfy_test/orchestration/manager.py
comfy_test/orchestration/results.py
comfy_test/platforms/__init__.py
comfy_test/platforms/linux/__init__.py
comfy_test/platforms/linux/ci.py
comfy_test/platforms/linux/local.py
comfy_test/platforms/linux/platform.py
comfy_test/platforms/macos/__init__.py
comfy_test/platforms/macos/ci.py
comfy_test/platforms/macos/local.py
comfy_test/platforms/macos/platform.py
comfy_test/platforms/windows/__init__.py
comfy_test/platforms/windows/ci.py
comfy_test/platforms/windows/isolation.py
comfy_test/platforms/windows/local.py
comfy_test/platforms/windows/platform.py
comfy_test/platforms/windows_portable/__init__.py
comfy_test/platforms/windows_portable/ci.py
comfy_test/platforms/windows_portable/download.py
comfy_test/platforms/windows_portable/local.py
comfy_test/platforms/windows_portable/platform.py
comfy_test/reporting/__init__.py
comfy_test/reporting/html_report.py
comfy_test/reporting/merge.py
comfy_test/reporting/screenshot.py
comfy_test/reporting/screenshot_cache.py
comfy_test-0.1.47.dist-info/METADATA
comfy_test-0.1.47.dist-info/WHEEL
comfy_test-0.1.47.dist-info/entry_points.txt
comfy_test-0.1.47.dist-info/licenses/LICENSE
comfy_test-0.1.47.dist-info/RECORD
