Metadata-Version: 2.4
Name: comfy-test
Version: 0.1.47
Summary: Installation testing infrastructure for ComfyUI custom nodes
Project-URL: Homepage, https://github.com/PozzettiAndrea/comfy-test
Project-URL: Repository, https://github.com/PozzettiAndrea/comfy-test
Project-URL: Issues, https://github.com/PozzettiAndrea/comfy-test/issues
Author: Andrea Pozzetti
License: MIT
License-File: LICENSE
Keywords: ci,comfyui,github-actions,installation,testing
Classifier: Development Status :: 3 - Alpha
Classifier: Intended Audience :: Developers
Classifier: License :: OSI Approved :: MIT License
Classifier: Programming Language :: Python :: 3.10
Classifier: Programming Language :: Python :: 3.11
Classifier: Programming Language :: Python :: 3.12
Classifier: Programming Language :: Python :: 3.13
Requires-Python: >=3.10
Requires-Dist: psutil>=5.9.0
Requires-Dist: py7zr>=0.20.0
Requires-Dist: requests>=2.28.0
Requires-Dist: tomli>=2.0.0; python_version < '3.11'
Requires-Dist: websocket-client
Provides-Extra: dev
Requires-Dist: mypy; extra == 'dev'
Requires-Dist: pytest; extra == 'dev'
Requires-Dist: ruff; extra == 'dev'
Provides-Extra: screenshot
Requires-Dist: pillow>=10.0.0; extra == 'screenshot'
Requires-Dist: playwright>=1.40.0; extra == 'screenshot'
